MANIFEST.in
README.md
setup.cfg
setup.py
datastory_standardizer.egg-info/PKG-INFO
datastory_standardizer.egg-info/SOURCES.txt
datastory_standardizer.egg-info/dependency_links.txt
datastory_standardizer.egg-info/requires.txt
datastory_standardizer.egg-info/top_level.txt
standardizer/__init__.py
standardizer/merge.py
standardizer/path.py
standardizer/entity/__init__.py
standardizer/entity/country.py
standardizer/indicator/__init__.py
standardizer/indicator/indicator.py
standardizer/ontology/ddf--entities--country.csv
standardizer/ontology/ddf--entities--country_alt_name.csv
standardizer/ontology/ddf--entities--indicator.csv
standardizer/ontology/ddf--entities--party.csv
standardizer/ontology/ddf--entities--region4.csv
standardizer/ontology/ddf--entities--region6.csv
standardizer/ontology/ddf--entities--source.csv
standardizer/ontology/lang/sv/ddf--entities--country.csv
standardizer/ontology/lang/sv/ddf--entities--country_alt_name.csv
standardizer/ontology/lang/sv/ddf--entities--indicator.csv
standardizer/ontology/lang/sv/ddf--entities--party.csv
standardizer/ontology/lang/sv/ddf--entities--region4.csv
standardizer/ontology/lang/sv/ddf--entities--region6.csv
standardizer/ontology/lang/sv/ddf--entities--source.csv
tests/__init__.py
tests/test_country_mapping.py
tests/test_ddf_wrappers.py
tests/test_indicator_mapping.py
tests/test_merge_packages.py