Metadata-Version: 1.0
Name: datastory-standardizer
Version: 0.5.0
Summary: Harmonizing Datastory data
Home-page: UNKNOWN
Author: Robin Linderborg
Author-email: robin@datastory.org
License: UNKNOWN
Platform: UNKNOWN
